{
  "pr_timestamps": [],
  "token_usage": 428260,
  "token_window_start": "2026-04-20T04:02:22.440901+00:00",
  "queued_failures": [],
  "ai_metrics": {
    "bedrock.invoke_schema.calls": 83,
    "bedrock.invoke_schema.success": 46,
    "bedrock.retrieval.calls": 326,
    "bedrock.retrieval.snippets": 680,
    "bedrock.retrieval.hits": 159,
    "bedrock.prompt_safety_guard.checked": 240,
    "bedrock.prompt_safety_guard.present": 240,
    "bedrock.tool_loop.calls": 72,
    "bedrock.tool_loop.turns": 974,
    "bedrock.tool_loop.success": 48,
    "reviewer.findings.normalized_kept": 4,
    "reviewer.verifier.kept": 4,
    "bedrock.tool_loop.terminal_validation_rejections": 204,
    "bedrock.retrieval.cache_hits": 68,
    "bedrock.errors.token_budget_exceeded": 8,
    "bedrock.invoke.calls": 87,
    "bedrock.tool_loop.forced_submissions": 21,
    "bedrock.tool_loop.thinking_enabled": 54,
    "bedrock.invoke_schema.thinking_enabled": 34,
    "bedrock.invoke.thinking_enabled": 83,
    "bedrock.errors.non_retryable": 43,
    "bedrock.invoke.success": 76,
    "bedrock.tool_loop.forced_submission_errors": 16,
    "bedrock.tool_loop.exhausted": 16,
    "bedrock.errors.input_too_large": 1,
    "bedrock.retrieval.errors": 8,
    "bedrock.retrieval.empty": 4,
    "bedrock.retrieval.degraded_analysis": 4
  }
}